larray_editor/__init__.py
larray_editor/api.py
larray_editor/arrayadapter.py
larray_editor/arraymodel.py
larray_editor/arraywidget.py
larray_editor/combo.py
larray_editor/commands.py
larray_editor/comparator.py
larray_editor/editor.py
larray_editor/sql.py
larray_editor/start.py
larray_editor/traceback_tools.py
larray_editor/utils.py
larray_editor/images/larray-help.ico
larray_editor/images/larray.ico
larray_editor/images/larray.png
larray_editor/images/larray.svg
larray_editor/tests/__init__.py
larray_editor/tests/run_with_console.py
larray_editor/tests/test_adapter.py
larray_editor/tests/test_api_larray.py
larray_editor/tests/test_inplace_modification_pattern.py
larray_editor-0.35.dist-info/licenses/LICENSE
larray_editor-0.35.dist-info/METADATA
larray_editor-0.35.dist-info/WHEEL
larray_editor-0.35.dist-info/entry_points.txt
larray_editor-0.35.dist-info/top_level.txt
larray_editor-0.35.dist-info/RECORD
